fastflexray/__init__.py
fastflexray/__main__.py
fastflexray-0.2.0.dist-info/entry_points.txt
fastflexray-0.2.0.dist-info/METADATA
fastflexray-0.2.0.dist-info/WHEEL
fastflexray-0.2.0.dist-info/RECORD
